linuxns_rel/__init__.py
linuxns_rel/tools/__init__.py
linuxns_rel/tools/lshierns.py
linuxns_rel/tools/viewer.py
linuxns_rel/tools/viewer_impl.py
linuxns_rel-1.0.6.dist-info/LICENSE
linuxns_rel-1.0.6.dist-info/METADATA
linuxns_rel-1.0.6.dist-info/WHEEL
linuxns_rel-1.0.6.dist-info/entry_points.txt
linuxns_rel-1.0.6.dist-info/top_level.txt
linuxns_rel-1.0.6.dist-info/RECORD
