Metadata-Version: 2.1
Name: linuxns-rel
Version: 1.0.6
Summary: Linux namespace relationships library
Home-page: https://github.com/TheDiveO/linuxns_rel
Author: TheDiveO
Author-email: thediveo@gmx.eu
License: Apache License 2.0
Platform: UNKNOWN
Classifier: Development Status :: 5 - Production/Stable
Classifier: Operating System :: POSIX :: Linux
Classifier: Programming Language :: Python :: 3.6
Classifier: Programming Language :: Python :: 3 :: Only
Classifier: License :: OSI Approved :: Apache Software License
Classifier: Topic :: Software Development :: Libraries
Classifier: Topic :: System :: Operating System Kernels :: Linux
Requires-Dist: psutil
Requires-Dist: asciitree
Requires-Dist: sty
Provides-Extra: dev
Requires-Dist: coverage ; extra == 'dev'
Requires-Dist: sphinx ; extra == 'dev'
Requires-Dist: sphinx-rtd-theme ; extra == 'dev'
Provides-Extra: graph
Requires-Dist: graphviz ; extra == 'graph'
Requires-Dist: PyQt5 ; extra == 'graph'
